[{"itemKey":"8000","itemName":"Sword_1","itemKorName":"Sword_1","attackType":"Melee","weaponType":"Sword","physicalDamage":"6","magicalDamage":"0","atkRange":"1","atkDistance":"1","atkSpeed":"3","equipLevel":"12","buyPrice":"2000","sellPrice":"1000","disassembleItemKey":"12012","disassembleItemAmount":"13","itemRank":"1"},{"itemKey":"8001","itemName":"Sword_2","itemKorName":"Sword_2","attackType":"Melee","weaponType":"Sword","physicalDamage":"12","magicalDamage":"0","atkRange":"1","atkDistance":"1","atkSpeed":"3","equipLevel":"13","buyPrice":"2000","sellPrice":"1000","disassembleItemKey":"12012","disassembleItemAmount":"14","itemRank":"1"},{"itemKey":"8002","itemName":"Sword_3","itemKorName":"Sword_3","attackType":"Melee","weaponType":"Sword","physicalDamage":"18","magicalDamage":"0","atkRange":"1","atkDistance":"1","atkSpeed":"3","equipLevel":"14","buyPrice":"2000","sellPrice":"1000","disassembleItemKey":"12012","disassembleItemAmount":"15","itemRank":"1"},{"itemKey":"8003","itemName":"Sword_4","itemKorName":"Sword_4","attackType":"Melee","weaponType":"Sword","physicalDamage":"24","magicalDamage":"0","atkRange":"1","atkDistance":"1","atkSpeed":"3","equipLevel":"15","buyPrice":"2000","sellPrice":"1000","disassembleItemKey":"12012","disassembleItemAmount":"16","itemRank":"1"},{"itemKey":"8004","itemName":"Sword_5","itemKorName":"Sword_5","attackType":"Melee","weaponType":"Sword","physicalDamage":"30","magicalDamage":"0","atkRange":"1","atkDistance":"1","atkSpeed":"3","equipLevel":"16","buyPrice":"2000","sellPrice":"1000","disassembleItemKey":"12012","disassembleItemAmount":"17","itemRank":"1"},{"itemKey":"8005","itemName":"Sword_6","itemKorName":"Sword_6","attackType":"Melee","weaponType":"Sword","physicalDamage":"35","magicalDamage":"0","atkRange":"1","atkDistance":"1","atkSpeed":"3","equipLevel":"17","buyPrice":"2000","sellPrice":"1000","disassembleItemKey":"12012","disassembleItemAmount":"18","itemRank":"1"},{"itemKey":"8006","itemName":"Sword_7","itemKorName":"Sword_7","attackType":"Melee","weaponType":"Sword","physicalDamage":"40","magicalDamage":"0","atkRange":"1","atkDistance":"1","atkSpeed":"3","equipLevel":"18","buyPrice":"2000","sellPrice":"1000","disassembleItemKey":"12012","disassembleItemAmount":"19","itemRank":"1"},{"itemKey":"8007","itemName":"Sword_8","itemKorName":"Sword_8","attackType":"Melee","weaponType":"Sword","physicalDamage":"45","magicalDamage":"0","atkRange":"1","atkDistance":"1","atkSpeed":"3","equipLevel":"19","buyPrice":"2000","sellPrice":"1000","disassembleItemKey":"12012","disassembleItemAmount":"20","itemRank":"1"},{"itemKey":"8008","itemName":"Sword_9","itemKorName":"Sword_9","attackType":"Melee","weaponType":"Sword","physicalDamage":"50","magicalDamage":"0","atkRange":"1","atkDistance":"1","atkSpeed":"3","equipLevel":"20","buyPrice":"2000","sellPrice":"1000","disassembleItemKey":"12012","disassembleItemAmount":"21","itemRank":"1"},{"itemKey":"8009","itemName":"Sword_10","itemKorName":"Sword_10","attackType":"Melee","weaponType":"Sword","physicalDamage":"55","magicalDamage":"0","atkRange":"1","atkDistance":"1","atkSpeed":"3","equipLevel":"21","buyPrice":"2000","sellPrice":"1000","disassembleItemKey":"12012","disassembleItemAmount":"22","itemRank":"1"},{"itemKey":"8010","itemName":"Sword_11","itemKorName":"Sword_11","attackType":"Melee","weaponType":"Sword","physicalDamage":"60","magicalDamage":"0","atkRange":"1","atkDistance":"1","atkSpeed":"3","equipLevel":"22","buyPrice":"2000","sellPrice":"1000","disassembleItemKey":"12012","disassembleItemAmount":"23","itemRank":"1"},{"itemKey":"8011","itemName":"Sword_12","itemKorName":"Sword_12","attackType":"Melee","weaponType":"Sword","physicalDamage":"65","magicalDamage":"0","atkRange":"1","atkDistance":"1","atkSpeed":"3","equipLevel":"23","buyPrice":"2000","sellPrice":"1000","disassembleItemKey":"12012","disassembleItemAmount":"24","itemRank":"1"},{"itemKey":"8012","itemName":"Sword_13","itemKorName":"Sword_13","attackType":"Melee","weaponType":"Sword","physicalDamage":"300","magicalDamage":"0","atkRange":"1","atkDistance":"1","atkSpeed":"1","equipLevel":"24","buyPrice":"2000","sellPrice":"1000","disassembleItemKey":"12012","disassembleItemAmount":"25","itemRank":"1"}]